wkmigrate/__init__.py
wkmigrate/_version.py
wkmigrate/activity_translators/__init__.py
wkmigrate/activity_translators/activity_translator.py
wkmigrate/activity_translators/for_each_activity_translator.py
wkmigrate/activity_translators/if_condition_activity_translator.py
wkmigrate/activity_translators/notebook_activity_translator.py
wkmigrate/activity_translators/parsers.py
wkmigrate/activity_translators/spark_jar_activity_translator.py
wkmigrate/activity_translators/spark_python_activity_translator.py
wkmigrate/definition_store_builder.py
wkmigrate/definition_stores/__init__.py
wkmigrate/definition_stores/definition_store.py
wkmigrate/definition_stores/factory_definition_store.py
wkmigrate/definition_stores/json_definition_store.py
wkmigrate/definition_stores/workspace_definition_store.py
wkmigrate/definition_stores/yaml_definition_store.py
wkmigrate/enums/__init__.py
wkmigrate/enums/compute_policy.py
wkmigrate/enums/condition_operation_pattern.py
wkmigrate/enums/init_script_type.py
wkmigrate/enums/interval_type.py
wkmigrate/enums/json_source_type.py
wkmigrate/linked_service_translators/__init__.py
wkmigrate/linked_service_translators/databricks_linked_service_translator.py
wkmigrate/linked_service_translators/parsers.py
wkmigrate/pipeline_translator.py
wkmigrate/pipeline_translators/__init__.py
wkmigrate/pipeline_translators/parameter_translator.py
wkmigrate/pipeline_translators/parsers.py
wkmigrate/trigger_translators/__init__.py
wkmigrate/trigger_translators/parsers.py
wkmigrate/trigger_translators/schedule_trigger_translator.py
wkmigrate/utils.py
wkmigrate-0.1.3.post1.dist-info/LICENSE
wkmigrate-0.1.3.post1.dist-info/METADATA
wkmigrate-0.1.3.post1.dist-info/WHEEL
wkmigrate-0.1.3.post1.dist-info/RECORD
